Workbook

Sheet README
A1: LYMBREXA forecast model — Week 6
A2: Applied Data Science and AI in Pharma Commercial · Columbia DSI · Fall 2026 · all data synthetic; LYMBREXA is fictional
A4: How to use
A5: 1. Choose a scenario on 'Assumptions' (cell C3): 1 = low, 2 = base, 3 = high. Every sheet recalculates.
A6: 2. Change any blue cell in the low / base / high columns on 'Assumptions' to test an assumption. Write the reason in the Rationale column.
A7: 3. Read the results on 'Brand_LRP' (annual, 2027–2041) and 'Budget' (monthly, 2027–2028).
A9: Colour code
A10: Blue text = input you may change · Black = formula · Green = link to another sheet · Yellow fill = scenario selector
A12: The model in five lines
A13: 1L patients = incident cases × diagnosed × treated in 1L
A14: 2L starts = last year's 1L patients × progress to 2L; 3L+ starts = last year's 2L × progress to 3L × later-lines multiplier
A15: Brand share = peak share × uptake (by year since launch) × coverage × LOE retention; new patients = line starts × brand share
... A24: Budget — the monthly budget for 2027–28

Sheet Assumptions
A1: Assumption book — LYMBREXA (3L+ and 2L DLBCL)
A3: Scenario (1 = low, 2 = base, 3 = high) | C3: 2
A5: ID | B5: Category | C5: Assumption | D5: Unit | E5: Low | F5: Base | G5: High | H5: Active | I5: Source type | J5: Source | K5: Rationale
A6: E0 | B6: Epidemiology | C6: Incident cases: multiplier on the data (Epi_Inputs) | D6: × data | E6: 0.95 | F6: 1 | G6: 1.05 | H6: =CHOOSE(Scenario,E6,F6,G6) -> 1 | I6: Data (synthetic) | J6: dlbcl_epi_inputs.csv (sum of age bands); Teras et al. 2016 for the age pattern | K6: Stylized US incidence; rises ~2%/yr as the population ages
A7: E1 | B7: Epidemiology | C7: Incident-case growth after 2030 | D7: % / yr | E7: 0.015 | F7: 0.023 | G7: 0.03 | H7: =CHOOSE(Scenario,E7,F7,G7) -> 0.023 | I7: Data (synthetic) | J7: 2026–2030 growth in dlbcl_epi_inputs.csv | K7: Continue the aging trend
A8: E2 | B8: Epidemiology | C8: Diagnosed and presenting | D8: % of cases | E8: 0.95 | F8: 0.97 | G8: 0.98 | H8: =CHOOSE(Scenario,E8,F8,G8) -> 0.97 | I8: Data (synthetic) | J8: dlbcl_treatment_funnel.csv, age-weighted | K8: Nearly all DLBCL is diagnosed — an aggressive lymphoma presents
A9: T1 | B9: Treatment | C9: Treated in 1L | D9: % of diagnosed | E9: 0.82 | F9: 0.86 | G9: 0.89 | H9: =CHOOSE(Scenario,E9,F9,G9) -> 0.86 | I9: Data (synthetic) | J9: dlbcl_treatment_funnel.csv, age-weighted | K9: Lower in the 80+ band; checked against observed 1L starts (within 2%)
A10: T2 | B10: Treatment | C10: Progress to 2L (lifetime), one year later | D10: % of 1L | E10: 0.26 | F10: 0.31 | G10: 0.36 | H10: =CHOOSE(Scenario,E10,F10,G10) -> 0.31 | I10: Data + literature | J10: Week 2 cohort, Kaplan–Meier 36% at 36 mo; Sehn & Salles 2021 (>60% cured with R-CHOP) | K10: KM on a treated claims cohort, trimmed for frail patients not re-treated
A11: T3 | B11: Treatment | C11: Progress to 3L (lifetime), one year later | D11: % of 2L | E11: 0.43 | F11: 0.5 | G11: 0.57 | H11: =CHOOSE(Scenario,E11,F11,G11) -> 0.5 | I11: Data + judgment | J11: Week 2 cohort, Kaplan–Meier 61% at 24 mo | K11: Cohort is younger than the market; adjusted down
A12: T4 | B12: Treatment | C12: Later-lines multiplier (3L+ starts per 3L patient) | D12: × | E12: 1.14 | F12: 1.24 | G12: 1.34 | H12: =CHOOSE(Scenario,E12,F12,G12) -> 1.24 | I12: Data (synthetic) | J12: dlbcl_treatment_funnel.csv | K12: Some 3L patients start a 4L and 5L
A13: T5 | B13: Treatment | C13: Lag between lines | D13: years | E13: 1 | F13: 1 | G13: 1 | H13: =CHOOSE(Scenario,E13,F13,G13) -> 1 | I13: Simplification | J13: Week 2 cohort: median 14 mo (1L→2L), 9 mo (2L→3L) | K13: Rounded to one year; acceptable at annual grain
A14: B1 | B14: Brand | C14: 3L+ launch year | D14: year | E14: 2027 | F14: 2027 | G14: 2027 | H14: =CHOOSE(Scenario,E14,F14,G14) -> 2027 | I14: Regulatory plan | J14: PDUFA January 2027 (fictional) | K14: A 3-month delay would cost ~6% of 2027 revenue; not modeled
A15: B2 | B15: Brand | C15: 2L label — first full year | D15: year | E15: 2030 | F15: 2029 | G15: 2028 | H15: =CHOOSE(Scenario,E15,F15,G15) -> 2029 | I15: Regulatory plan | J15: Phase 3 readout; sBLA mid-2028 (fictional) | K15: Base models 2L from Jan 2029; high case brings it to 2028
A16: B3 | B16: Brand | C16: Peak share of 3L+ starts | D16: % of starts | E16: 0.1 | F16: 0.15 | G16: 0.2 | H16: =CHOOSE(Scenario,E16,F16,G16) -> 0.15 | I16: Literature + analog | J16: Kalyanaram, Robinson & Urban 1995: share ≈ pioneer ÷ √order → 0.26 × 0.58 | K16: Third entrant in class; pioneer analog peaked at 0.26
A17: B4 | B17: Brand | C17: Peak share of 2L starts | D17: % of starts | E17: 0.06 | F17: 0.1 | G17: 0.14 | H17: =CHOOSE(Scenario,E17,F17,G17) -> 0.1 | I17: Judgment | J17: 2L crowded: CAR-T, ADC combination, chemo-immunotherapy | K17: Lower than 3L+ because the 2L market has more options
A18: U1 | B18: Brand | C18: Uptake: year 1 (% of peak share) | D18: % of peak | E18: 0.15 | F18: 0.3 | G18: 0.37 | H18: =CHOOSE(Scenario,E18,F18,G18) -> 0.3 | I18: Analog | J18: analog_launches_monthly.csv: outpatient analogs 0.24–0.37; CAR-T 0.08–0.12 | K18: Low = cell-therapy-like start; high = first bispecific
A19: U2 | B19: Brand | C19: Uptake: year 2 | D19: % of peak | E19: 0.6 | F19: 0.9 | G19: 0.95 | H19: =CHOOSE(Scenario,E19,F19,G19) -> 0.9 | I19: Analog | J19: same: outpatient 0.89–0.99; CAR-T 0.49–0.63
A20: U3 | B20: Brand | C20: Uptake: year 3 | D20: % of peak | E20: 0.95 | F20: 1 | G20: 1 | H20: =CHOOSE(Scenario,E20,F20,G20) -> 1 | I20: Analog | J20: same: all analogs 0.90–1.06
A21: U4 | B21: Brand | C21: Uptake: year 4 onward | D21: % of peak | E21: 1 | F21: 1 | G21: 1 | H21: =CHOOSE(Scenario,E21,F21,G21) -> 1 | I21: Analog | J21: same | K21: Peak by year 3–4
A22: C1 | B22: Access | C22: Coverage in launch year | D22: % of starts reachable | E22: 0.55 | F22: 0.7 | G22: 0.85 | H22: =CHOOSE(Scenario,E22,F22,G22) -> 0.7 | I22: Data + judgment | J22: dlbcl_prescriber_3Lplus_starts.csv: top 10% of prescribers write 53% of starts | K22: Formulary at the ~40 largest centers in year 1
A23: C2 | B23: Access | C23: Coverage from year 2 | D23: % of starts reachable | E23: 0.9 | F23: 0.95 | G23: 0.97 | H23: =CHOOSE(Scenario,E23,F23,G23) -> 0.95 | I23: Judgment | J23: Long tail of community prescribers
A24: D1 | B24: Persistence | C24: Average months on therapy | D24: months | E24: 5 | F24: 6 | G24: 7.5 | H24: =CHOOSE(Scenario,E24,F24,G24) -> 6 | I24: Label + data | J24: 8-cycle fixed course (label, fictional); persistence KM: analogs 5.9–9.4 mo; Cramer et al. 2008 definitions | K24: Cap of 8 months minus early discontinuation
A25: D2 | B25: Persistence | C25: Compliance (doses received) | D25: % of planned | E25: 0.92 | F25: 0.95 | G25: 0.97 | H25: =CHOOSE(Scenario,E25,F25,G25) -> 0.95 | I25: Judgment | J25: Dose delays and holds
A26: P1 | B26: Price | C26: List price (WAC) per 28-day month | D26: $ | E26: 18500 | F26: 18500 | G26: 18500 | H26: =CHOOSE(Scenario,E26,F26,G26) -> 18500 | I26: Pricing plan | J26: Fictional | K26: Held flat (no price increases modeled)
A27: P2 | B27: Price | C27: Gross-to-net (share of WAC kept) | D27: % | E27: 0.72 | F27: 0.76 | G27: 0.8 | H27: =CHOOSE(Scenario,E27,F27,G27) -> 0.76 | I27: Judgment | J27: Rebates, 340B, Medicare
A28: L1 | B28: LOE | C28: Loss-of-exclusivity year | D28: year | E28: 2038 | F28: 2039 | G28: 2040 | H28: =CHOOSE(Scenario,E28,F28,G28) -> 2039 | I28: Patent calendar | J28: Fictional; see IQVIA ADC paper for how exclusivity dates are read
A29: L2 | B29: LOE | C29: Share retained in the LOE year | D29: % of pre-LOE | E29: 0.65 | F29: 0.75 | G29: 0.85 | H29: =CHOOSE(Scenario,E29,F29,G29) -> 0.75 | I29: Judgment | J29: Mid-year entry
A30: L3 | B30: LOE | C30: Share retained after the LOE year | D30: % of pre-LOE | E30: 0.25 | F30: 0.4 | G30: 0.55 | H30: =CHOOSE(Scenario,E30,F30,G30) -> 0.4 | I30: Literature + judgment | J30: Grabowski et al. 2021: small-molecule brands keep ~23% of units at 1 yr; biologics erode slower | K30: Biosimilar erosion assumed slower than generic
A31: F1 | B31: Budget | C31: Launch-year phasing of starts | D31: profile | F31: linear ramp (month m ∝ m) | I31: Simplification | K31: Starts grow through the launch year
A32: F2 | B32: Budget | C32: Phasing after the launch year | D32: profile | F32: flat (1/12 per month) | I32: Simplification | K32: No seasonality in oncology starts
A34: Plan of record (for comparison)
A35: LRP 2029 net revenue ($M) | F35: 250 | J35: Portfolio strategy plan on file (case input)
A36: LRP peak net revenue ($M) | F36: 400 | J36: Portfolio strategy plan on file (case input)

Sheet Epi_Inputs
A1: Incident DLBCL cases (US, all ages)
A2: Source: dlbcl_epi_inputs.csv (synthetic, stylized; age pattern per Teras et al., CA Cancer J Clin 2016). After 2030: grows at Case_growth.
A4: Year | B4: Incident cases
A5: 2022 | B5: 20524
A6: 2023 | B6: 20974
A7: 2024 | B7: 21437
A8: 2025 | B8: 21913
A9: 2026 | B9: 22404
A10: 2027 | B10: 22910
A11: 2028 | B11: 23430
A12: 2029 | B12: 23966
A13: 2030 | B13: 24519
A14: 2031 | B14: =B13*(1+Case_growth) -> 25082.937
A15: 2032 | B15: =B14*(1+Case_growth) -> 25659.845
A16: 2033 | B16: =B15*(1+Case_growth) -> 26250.021
A17: 2034 | B17: =B16*(1+Case_growth) -> 26853.771
A18: 2035 | B18: =B17*(1+Case_growth) -> 27471.408
A19: 2036 | B19: =B18*(1+Case_growth) -> 28103.251
A20: 2037 | B20: =B19*(1+Case_growth) -> 28749.625
A21: 2038 | B21: =B20*(1+Case_growth) -> 29410.867
A22: 2039 | B22: =B21*(1+Case_growth) -> 30087.317
A23: 2040 | B23: =B22*(1+Case_growth) -> 30779.325
A24: 2041 | B24: =B23*(1+Case_growth) -> 31487.249

Sheet Funnel
A1: The patient funnel — incidence model, one-year lag between lines
B3: 2022 | C3: 2023 | D3: 2024 | E3: 2025 | F3: 2026 | G3: 2027 | H3: 2028 | I3: 2029 | J3: 2030 | K3: 2031 | L3: 2032 | M3: 2033 | N3: 2034 | O3: 2035 | P3: 2036 | Q3: 2037 | R3: 2038 | S3: 2039 | T3: 2040 | U3: 2041
A4: Incident cases | B4: =Epi_Inputs!B5*Cases_multiplier -> 20524 | C4: =Epi_Inputs!B6*Cases_multiplier -> 20974 | D4: =Epi_Inputs!B7*Cases_multiplier -> 21437 | E4: =Epi_Inputs!B8*Cases_multiplier -> 21913 | F4: =Epi_Inputs!B9*Cases_multiplier -> 22404 | G4: =Epi_Inputs!B10*Cases_multiplier -> 22910 | H4: =Epi_Inputs!B11*Cases_multiplier -> 23430 | I4: =Epi_Inputs!B12*Cases_multiplier -> 23966 | J4: =Epi_Inputs!B13*Cases_multiplier -> 24519 | K4: =Epi_Inputs!B14*Cases_multiplier -> 25082.937 | L4: =Epi_Inputs!B15*Cases_multiplier -> 25659.845 | M4: =Epi_Inputs!B16*Cases_multiplier -> 26250.021 | N4: =Epi_Inputs!B17*Cases_multiplier -> 26853.771 | O4: =Epi_Inputs!B18*Cases_multiplier -> 27471.408 | P4: =Epi_Inputs!B19*Cases_multiplier -> 28103.251 | Q4: =Epi_Inputs!B20*Cases_multiplier -> 28749.625 | R4: =Epi_Inputs!B21*Cases_multiplier -> 29410.867 | S4: =Epi_Inputs!B22*Cases_multiplier -> 30087.317 | T4: =Epi_Inputs!B23*Cases_multiplier -> 30779.325 | U4: =Epi_Inputs!B24*Cases_multiplier -> 31487.249
A5: Diagnosed and presenting | B5: =B4*Diagnosed -> 19908.28 | C5: =C4*Diagnosed -> 20344.78 | D5: =D4*Diagnosed -> 20793.89 | E5: =E4*Diagnosed -> 21255.61 | F5: =F4*Diagnosed -> 21731.88 | G5: =G4*Diagnosed -> 22222.7 | H5: =H4*Diagnosed -> 22727.1 | I5: =I4*Diagnosed -> 23247.02 | ... U5: =U4*Diagnosed -> 30542.632
A6: Treated in 1L | B6: =B5*Treated_1L -> 17121.121 | C6: =C5*Treated_1L -> 17496.511 | D6: =D5*Treated_1L -> 17882.745 | E6: =E5*Treated_1L -> 18279.825 | F6: =F5*Treated_1L -> 18689.417 | G6: =G5*Treated_1L -> 19111.522 | H6: =H5*Treated_1L -> 19545.306 | I6: =I5*Treated_1L -> 19992.437 | ... U6: =U5*Treated_1L -> 26266.663
A7: 2L treatment starts | C7: =B6*Progress_2L -> 5307.5474 | D7: =C6*Progress_2L -> 5423.9183 | E7: =D6*Progress_2L -> 5543.6511 | F7: =E6*Progress_2L -> 5666.7456 | G7: =F6*Progress_2L -> 5793.7192 | H7: =G6*Progress_2L -> 5924.5718 | I7: =H6*Progress_2L -> 6059.0449 | J7: =I6*Progress_2L -> 6197.6555 | ... U7: =T6*Progress_2L -> 7959.595
A8: 3L+ treatment starts | D8: =C7*Progress_3L*Later_lines -> 3290.6794 | E8: =D7*Progress_3L*Later_lines -> 3362.8294 | F8: =E7*Progress_3L*Later_lines -> 3437.0637 | G8: =F7*Progress_3L*Later_lines -> 3513.3823 | H8: =G7*Progress_3L*Later_lines -> 3592.1059 | I8: =H7*Progress_3L*Later_lines -> 3673.2345 | J8: =I7*Progress_3L*Later_lines -> 3756.6078 | K8: =J7*Progress_3L*Later_lines -> 3842.5464 | ... U8: =T7*Progress_3L*Later_lines -> 4823.997
A10: Check against the market (2025): observed 1L 17,930 · 2L 5,468 · 3L+ 3,471 (dlbcl_market_monthly.csv)

Sheet Brand_LRP
A1: LYMBREXA — long-range plan (annual)
B3: 2022 | C3: 2023 | D3: 2024 | E3: 2025 | F3: 2026 | G3: 2027 | H3: 2028 | I3: 2029 | J3: 2030 | K3: 2031 | L3: 2032 | M3: 2033 | N3: 2034 | O3: 2035 | P3: 2036 | Q3: 2037 | R3: 2038 | S3: 2039 | T3: 2040 | U3: 2041
A4: 3L+ indication
A5: Years since 3L+ launch | B5: =VALUE(B$3)-Launch_3L+1 -> -4 | C5: =VALUE(C$3)-Launch_3L+1 -> -3 | D5: =VALUE(D$3)-Launch_3L+1 -> -2 | E5: =VALUE(E$3)-Launch_3L+1 -> -1 | F5: =VALUE(F$3)-Launch_3L+1 -> 0 | G5: =VALUE(G$3)-Launch_3L+1 -> 1 | H5: =VALUE(H$3)-Launch_3L+1 -> 2 | I5: =VALUE(I$3)-Launch_3L+1 -> 3 | ... U5: =VALUE(U$3)-Launch_3L+1 -> 15
A6: Uptake (% of peak share) | B6: =IF(B5<1,0,CHOOSE(MIN(B5,4),Uptake_Y1,Uptake_Y2,Uptake_Y3,Uptake_Y4)) -> 0 | C6: =IF(C5<1,0,CHOOSE(MIN(C5,4),Uptake_Y1,Uptake_Y2,Uptake_Y3,Uptake_Y4)) -> 0 | D6: =IF(D5<1,0,CHOOSE(MIN(D5,4),Uptake_Y1,Uptake_Y2,Uptake_Y3,Uptake_Y4)) -> 0 | E6: =IF(E5<1,0,CHOOSE(MIN(E5,4),Uptake_Y1,Uptake_Y2,Uptake_Y3,Uptake_Y4)) -> 0 | F6: =IF(F5<1,0,CHOOSE(MIN(F5,4),Uptake_Y1,Uptake_Y2,Uptake_Y3,Uptake_Y4)) -> 0 | G6: =IF(G5<1,0,CHOOSE(MIN(G5,4),Uptake_Y1,Uptake_Y2,Uptake_Y3,Uptake_Y4)) -> 0.3 | H6: =IF(H5<1,0,CHOOSE(MIN(H5,4),Uptake_Y1,Uptake_Y2,Uptake_Y3,Uptake_Y4)) -> 0.9 | I6: =IF(I5<1,0,CHOOSE(MIN(I5,4),Uptake_Y1,Uptake_Y2,Uptake_Y3,Uptake_Y4)) -> 1 | ... U6: =IF(U5<1,0,CHOOSE(MIN(U5,4),Uptake_Y1,Uptake_Y2,Uptake_Y3,Uptake_Y4)) -> 1
A7: Coverage | B7: =IF(B5<1,0,IF(B5=1,Coverage_Y1,Coverage_Y2)) -> 0 | C7: =IF(C5<1,0,IF(C5=1,Coverage_Y1,Coverage_Y2)) -> 0 | D7: =IF(D5<1,0,IF(D5=1,Coverage_Y1,Coverage_Y2)) -> 0 | E7: =IF(E5<1,0,IF(E5=1,Coverage_Y1,Coverage_Y2)) -> 0 | F7: =IF(F5<1,0,IF(F5=1,Coverage_Y1,Coverage_Y2)) -> 0 | G7: =IF(G5<1,0,IF(G5=1,Coverage_Y1,Coverage_Y2)) -> 0.7 | H7: =IF(H5<1,0,IF(H5=1,Coverage_Y1,Coverage_Y2)) -> 0.95 | I7: =IF(I5<1,0,IF(I5=1,Coverage_Y1,Coverage_Y2)) -> 0.95 | ... U7: =IF(U5<1,0,IF(U5=1,Coverage_Y1,Coverage_Y2)) -> 0.95
A8: LOE retention | B8: =IF(VALUE(B$3)<LOE_year,1,IF(VALUE(B$3)=LOE_year,LOE_retention_Y0,LOE_retention_after)) -> 1 | C8: =IF(VALUE(C$3)<LOE_year,1,IF(VALUE(C$3)=LOE_year,LOE_retention_Y0,LOE_retention_after)) -> 1 | D8: =IF(VALUE(D$3)<LOE_year,1,IF(VALUE(D$3)=LOE_year,LOE_retention_Y0,LOE_retention_after)) -> 1 | E8: =IF(VALUE(E$3)<LOE_year,1,IF(VALUE(E$3)=LOE_year,LOE_retention_Y0,LOE_retention_after)) -> 1 | F8: =IF(VALUE(F$3)<LOE_year,1,IF(VALUE(F$3)=LOE_year,LOE_retention_Y0,LOE_retention_after)) -> 1 | G8: =IF(VALUE(G$3)<LOE_year,1,IF(VALUE(G$3)=LOE_year,LOE_retention_Y0,LOE_retention_after)) -> 1 | H8: =IF(VALUE(H$3)<LOE_year,1,IF(VALUE(H$3)=LOE_year,LOE_retention_Y0,LOE_retention_after)) -> 1 | I8: =IF(VALUE(I$3)<LOE_year,1,IF(VALUE(I$3)=LOE_year,LOE_retention_Y0,LOE_retention_after)) -> 1 | ... U8: =IF(VALUE(U$3)<LOE_year,1,IF(VALUE(U$3)=LOE_year,LOE_retention_Y0,LOE_retention_after)) -> 0.4
A9: Brand share of 3L+ starts | B9: =Peak_share_3L*B6*B7*B8 -> 0 | C9: =Peak_share_3L*C6*C7*C8 -> 0 | D9: =Peak_share_3L*D6*D7*D8 -> 0 | E9: =Peak_share_3L*E6*E7*E8 -> 0 | F9: =Peak_share_3L*F6*F7*F8 -> 0 | G9: =Peak_share_3L*G6*G7*G8 -> 0.0315 | H9: =Peak_share_3L*H6*H7*H8 -> 0.12825 | I9: =Peak_share_3L*I6*I7*I8 -> 0.1425 | ... U9: =Peak_share_3L*U6*U7*U8 -> 0.057
A10: New 3L+ patients | B10: =IF(ISNUMBER(Funnel!B8),Funnel!B8,0)*B9 -> 0 | C10: =IF(ISNUMBER(Funnel!C8),Funnel!C8,0)*C9 -> 0 | D10: =IF(ISNUMBER(Funnel!D8),Funnel!D8,0)*D9 -> 0 | E10: =IF(ISNUMBER(Funnel!E8),Funnel!E8,0)*E9 -> 0 | F10: =IF(ISNUMBER(Funnel!F8),Funnel!F8,0)*F9 -> 0 | G10: =IF(ISNUMBER(Funnel!G8),Funnel!G8,0)*G9 -> 110.67154 | H10: =IF(ISNUMBER(Funnel!H8),Funnel!H8,0)*H9 -> 460.68758 | I10: =IF(ISNUMBER(Funnel!I8),Funnel!I8,0)*I9 -> 523.43592 | ... U10: =IF(ISNUMBER(Funnel!U8),Funnel!U8,0)*U9 -> 274.96783
A11: 2L indication
A12: Years since 2L launch | B12: =VALUE(B$3)-Launch_2L+1 -> -6 | C12: =VALUE(C$3)-Launch_2L+1 -> -5 | D12: =VALUE(D$3)-Launch_2L+1 -> -4 | E12: =VALUE(E$3)-Launch_2L+1 -> -3 | F12: =VALUE(F$3)-Launch_2L+1 -> -2 | G12: =VALUE(G$3)-Launch_2L+1 -> -1 | H12: =VALUE(H$3)-Launch_2L+1 -> 0 | I12: =VALUE(I$3)-Launch_2L+1 -> 1 | ... U12: =VALUE(U$3)-Launch_2L+1 -> 13
A13: Uptake (% of peak share) | B13: =IF(B12<1,0,CHOOSE(MIN(B12,4),Uptake_Y1,Uptake_Y2,Uptake_Y3,Uptake_Y4)) -> 0 | C13: =IF(C12<1,0,CHOOSE(MIN(C12,4),Uptake_Y1,Uptake_Y2,Uptake_Y3,Uptake_Y4)) -> 0 | D13: =IF(D12<1,0,CHOOSE(MIN(D12,4),Uptake_Y1,Uptake_Y2,Uptake_Y3,Uptake_Y4)) -> 0 | E13: =IF(E12<1,0,CHOOSE(MIN(E12,4),Uptake_Y1,Uptake_Y2,Uptake_Y3,Uptake_Y4)) -> 0 | F13: =IF(F12<1,0,CHOOSE(MIN(F12,4),Uptake_Y1,Uptake_Y2,Uptake_Y3,Uptake_Y4)) -> 0 | G13: =IF(G12<1,0,CHOOSE(MIN(G12,4),Uptake_Y1,Uptake_Y2,Uptake_Y3,Uptake_Y4)) -> 0 | H13: =IF(H12<1,0,CHOOSE(MIN(H12,4),Uptake_Y1,Uptake_Y2,Uptake_Y3,Uptake_Y4)) -> 0 | I13: =IF(I12<1,0,CHOOSE(MIN(I12,4),Uptake_Y1,Uptake_Y2,Uptake_Y3,Uptake_Y4)) -> 0.3 | ... U13: =IF(U12<1,0,CHOOSE(MIN(U12,4),Uptake_Y1,Uptake_Y2,Uptake_Y3,Uptake_Y4)) -> 1
A14: Coverage | B14: =IF(B12<1,0,IF(B12=1,Coverage_Y1,Coverage_Y2)) -> 0 | C14: =IF(C12<1,0,IF(C12=1,Coverage_Y1,Coverage_Y2)) -> 0 | D14: =IF(D12<1,0,IF(D12=1,Coverage_Y1,Coverage_Y2)) -> 0 | E14: =IF(E12<1,0,IF(E12=1,Coverage_Y1,Coverage_Y2)) -> 0 | F14: =IF(F12<1,0,IF(F12=1,Coverage_Y1,Coverage_Y2)) -> 0 | G14: =IF(G12<1,0,IF(G12=1,Coverage_Y1,Coverage_Y2)) -> 0 | H14: =IF(H12<1,0,IF(H12=1,Coverage_Y1,Coverage_Y2)) -> 0 | I14: =IF(I12<1,0,IF(I12=1,Coverage_Y1,Coverage_Y2)) -> 0.7 | ... U14: =IF(U12<1,0,IF(U12=1,Coverage_Y1,Coverage_Y2)) -> 0.95
A15: Brand share of 2L starts | B15: =Peak_share_2L*B13*B14*B8 -> 0 | C15: =Peak_share_2L*C13*C14*C8 -> 0 | D15: =Peak_share_2L*D13*D14*D8 -> 0 | E15: =Peak_share_2L*E13*E14*E8 -> 0 | F15: =Peak_share_2L*F13*F14*F8 -> 0 | G15: =Peak_share_2L*G13*G14*G8 -> 0 | H15: =Peak_share_2L*H13*H14*H8 -> 0 | I15: =Peak_share_2L*I13*I14*I8 -> 0.021 | ... U15: =Peak_share_2L*U13*U14*U8 -> 0.038
A16: New 2L patients | B16: =IF(ISNUMBER(Funnel!B7),Funnel!B7,0)*B15 -> 0 | C16: =IF(ISNUMBER(Funnel!C7),Funnel!C7,0)*C15 -> 0 | D16: =IF(ISNUMBER(Funnel!D7),Funnel!D7,0)*D15 -> 0 | E16: =IF(ISNUMBER(Funnel!E7),Funnel!E7,0)*E15 -> 0 | F16: =IF(ISNUMBER(Funnel!F7),Funnel!F7,0)*F15 -> 0 | G16: =IF(ISNUMBER(Funnel!G7),Funnel!G7,0)*G15 -> 0 | H16: =IF(ISNUMBER(Funnel!H7),Funnel!H7,0)*H15 -> 0 | I16: =IF(ISNUMBER(Funnel!I7),Funnel!I7,0)*I15 -> 127.23994 | ... U16: =IF(ISNUMBER(Funnel!U7),Funnel!U7,0)*U15 -> 302.46461
A17: Totals
A18: New patients | B18: =B10+B16 -> 0 | C18: =C10+C16 -> 0 | D18: =D10+D16 -> 0 | E18: =E10+E16 -> 0 | F18: =F10+F16 -> 0 | G18: =G10+G16 -> 110.67154 | H18: =H10+H16 -> 460.68758 | I18: =I10+I16 -> 650.67586 | ... U18: =U10+U16 -> 577.43244
A19: Patients on therapy (average) | B19: =B18*Months_on_therapy/12 -> 0 | C19: =C18*Months_on_therapy/12 -> 0 | D19: =D18*Months_on_therapy/12 -> 0 | E19: =E18*Months_on_therapy/12 -> 0 | F19: =F18*Months_on_therapy/12 -> 0 | G19: =G18*Months_on_therapy/12 -> 55.335771 | H19: =H18*Months_on_therapy/12 -> 230.34379 | I19: =I18*Months_on_therapy/12 -> 325.33793 | ... U19: =U18*Months_on_therapy/12 -> 288.71622
A20: Patient-months | B20: =B18*Months_on_therapy -> 0 | C20: =C18*Months_on_therapy -> 0 | D20: =D18*Months_on_therapy -> 0 | E20: =E18*Months_on_therapy -> 0 | F20: =F18*Months_on_therapy -> 0 | G20: =G18*Months_on_therapy -> 664.02925 | H20: =H18*Months_on_therapy -> 2764.1255 | I20: =I18*Months_on_therapy -> 3904.0552 | ... U20: =U18*Months_on_therapy -> 3464.5946
A21: Net revenue ($M) | B21: =B20*Compliance*WAC_month*Gross_to_net/1000000 -> 0 | C21: =C20*Compliance*WAC_month*Gross_to_net/1000000 -> 0 | D21: =D20*Compliance*WAC_month*Gross_to_net/1000000 -> 0 | E21: =E20*Compliance*WAC_month*Gross_to_net/1000000 -> 0 | F21: =F20*Compliance*WAC_month*Gross_to_net/1000000 -> 0 | G21: =G20*Compliance*WAC_month*Gross_to_net/1000000 -> 8.8694387 | H21: =H20*Compliance*WAC_month*Gross_to_net/1000000 -> 36.920424 | I21: =I20*Compliance*WAC_month*Gross_to_net/1000000 -> 52.146465 | ... U21: =U20*Compliance*WAC_month*Gross_to_net/1000000 -> 46.27659
A22: Plan of record ($M) | I22: =Plan_2029 -> 250
A24: Peak net revenue ($M) | B24: =MAX(B21:U21) -> 108.06236
A25: Peak year | B25: =INDEX(B3:U3,MATCH(B24,B21:U21,0)) -> 2038
A26: Plan of record, peak ($M) | B26: =Plan_peak -> 400
A28: Patients on therapy uses Little's law (Little 1961): average on therapy = starts per year × years on therapy. It slightly overstates the launch year.

Sheet Budget
A1: LYMBREXA — budget (monthly, 2027–28) = the LRP phased by month
A2: Phasing: in the launch year, month m gets m/78 of the year (linear ramp; 1+2+…+12 = 78); later years 1/12 each (assumptions F1, F2).
A4: Month | B4: Year | C4: Month # | D4: Phasing weight | E4: New patients | F4: Patients on therapy | G4: Vials | H4: Net revenue ($M)
A5: 2027-01 | B5: 2027 | C5: 1 | D5: =IF(VALUE(B5)=Launch_3L,C5/78,1/12) -> 0.012820513 | E5: =INDEX(Brand_LRP!$B$18:$U$18,MATCH(B5,Brand_LRP!$B$3:$U$3,0))*D5 -> 1.4188659 | F5: =INDEX(Brand_LRP!$B$19:$U$19,MATCH(B5,Brand_LRP!$B$3:$U$3,0))*12*D5 -> 8.5131955 | G5: =F5*Compliance -> 8.0875358 | H5: =INDEX(Brand_LRP!$B$21:$U$21,MATCH(B5,Brand_LRP!$B$3:$U$3,0))*D5 -> 0.11371075
A6: 2027-02 | B6: 2027 | C6: 2 | D6: =IF(VALUE(B6)=Launch_3L,C6/78,1/12) -> 0.025641026 | E6: =INDEX(Brand_LRP!$B$18:$U$18,MATCH(B6,Brand_LRP!$B$3:$U$3,0))*D6 -> 2.8377318 | F6: =INDEX(Brand_LRP!$B$19:$U$19,MATCH(B6,Brand_LRP!$B$3:$U$3,0))*12*D6 -> 17.026391 | G6: =F6*Compliance -> 16.175072 | H6: =INDEX(Brand_LRP!$B$21:$U$21,MATCH(B6,Brand_LRP!$B$3:$U$3,0))*D6 -> 0.22742151
A7: 2027-03 | B7: 2027 | C7: 3 | D7: =IF(VALUE(B7)=Launch_3L,C7/78,1/12) -> 0.038461538 | E7: =INDEX(Brand_LRP!$B$18:$U$18,MATCH(B7,Brand_LRP!$B$3:$U$3,0))*D7 -> 4.2565978 | F7: =INDEX(Brand_LRP!$B$19:$U$19,MATCH(B7,Brand_LRP!$B$3:$U$3,0))*12*D7 -> 25.539587 | G7: =F7*Compliance -> 24.262607 | H7: =INDEX(Brand_LRP!$B$21:$U$21,MATCH(B7,Brand_LRP!$B$3:$U$3,0))*D7 -> 0.34113226
A8: 2027-04 | B8: 2027 | C8: 4 | D8: =IF(VALUE(B8)=Launch_3L,C8/78,1/12) -> 0.051282051 | E8: =INDEX(Brand_LRP!$B$18:$U$18,MATCH(B8,Brand_LRP!$B$3:$U$3,0))*D8 -> 5.6754637 | F8: =INDEX(Brand_LRP!$B$19:$U$19,MATCH(B8,Brand_LRP!$B$3:$U$3,0))*12*D8 -> 34.052782 | G8: =F8*Compliance -> 32.350143 | H8: =INDEX(Brand_LRP!$B$21:$U$21,MATCH(B8,Brand_LRP!$B$3:$U$3,0))*D8 -> 0.45484301
A9: 2027-05 | B9: 2027 | C9: 5 | D9: =IF(VALUE(B9)=Launch_3L,C9/78,1/12) -> 0.064102564 | E9: =INDEX(Brand_LRP!$B$18:$U$18,MATCH(B9,Brand_LRP!$B$3:$U$3,0))*D9 -> 7.0943296 | F9: =INDEX(Brand_LRP!$B$19:$U$19,MATCH(B9,Brand_LRP!$B$3:$U$3,0))*12*D9 -> 42.565978 | G9: =F9*Compliance -> 40.437679 | H9: =INDEX(Brand_LRP!$B$21:$U$21,MATCH(B9,Brand_LRP!$B$3:$U$3,0))*D9 -> 0.56855376
A10: 2027-06 | B10: 2027 | C10: 6 | D10: =IF(VALUE(B10)=Launch_3L,C10/78,1/12) -> 0.076923077 | E10: =INDEX(Brand_LRP!$B$18:$U$18,MATCH(B10,Brand_LRP!$B$3:$U$3,0))*D10 -> 8.5131955 | F10: =INDEX(Brand_LRP!$B$19:$U$19,MATCH(B10,Brand_LRP!$B$3:$U$3,0))*12*D10 -> 51.079173 | G10: =F10*Compliance -> 48.525215 | H10: =INDEX(Brand_LRP!$B$21:$U$21,MATCH(B10,Brand_LRP!$B$3:$U$3,0))*D10 -> 0.68226452
A11: 2027-07 | B11: 2027 | C11: 7 | D11: =IF(VALUE(B11)=Launch_3L,C11/78,1/12) -> 0.08974359 | E11: =INDEX(Brand_LRP!$B$18:$U$18,MATCH(B11,Brand_LRP!$B$3:$U$3,0))*D11 -> 9.9320615 | F11: =INDEX(Brand_LRP!$B$19:$U$19,MATCH(B11,Brand_LRP!$B$3:$U$3,0))*12*D11 -> 59.592369 | G11: =F11*Compliance -> 56.61275 | H11: =INDEX(Brand_LRP!$B$21:$U$21,MATCH(B11,Brand_LRP!$B$3:$U$3,0))*D11 -> 0.79597527
A12: 2027-08 | B12: 2027 | C12: 8 | D12: =IF(VALUE(B12)=Launch_3L,C12/78,1/12) -> 0.1025641 | E12: =INDEX(Brand_LRP!$B$18:$U$18,MATCH(B12,Brand_LRP!$B$3:$U$3,0))*D12 -> 11.350927 | F12: =INDEX(Brand_LRP!$B$19:$U$19,MATCH(B12,Brand_LRP!$B$3:$U$3,0))*12*D12 -> 68.105564 | G12: =F12*Compliance -> 64.700286 | H12: =INDEX(Brand_LRP!$B$21:$U$21,MATCH(B12,Brand_LRP!$B$3:$U$3,0))*D12 -> 0.90968602
A13: 2027-09 | B13: 2027 | C13: 9 | D13: =IF(VALUE(B13)=Launch_3L,C13/78,1/12) -> 0.11538462 | E13: =INDEX(Brand_LRP!$B$18:$U$18,MATCH(B13,Brand_LRP!$B$3:$U$3,0))*D13 -> 12.769793 | F13: =INDEX(Brand_LRP!$B$19:$U$19,MATCH(B13,Brand_LRP!$B$3:$U$3,0))*12*D13 -> 76.61876 | G13: =F13*Compliance -> 72.787822 | H13: =INDEX(Brand_LRP!$B$21:$U$21,MATCH(B13,Brand_LRP!$B$3:$U$3,0))*D13 -> 1.0233968
A14: 2027-10 | B14: 2027 | C14: 10 | D14: =IF(VALUE(B14)=Launch_3L,C14/78,1/12) -> 0.12820513 | E14: =INDEX(Brand_LRP!$B$18:$U$18,MATCH(B14,Brand_LRP!$B$3:$U$3,0))*D14 -> 14.188659 | F14: =INDEX(Brand_LRP!$B$19:$U$19,MATCH(B14,Brand_LRP!$B$3:$U$3,0))*12*D14 -> 85.131955 | G14: =F14*Compliance -> 80.875358 | H14: =INDEX(Brand_LRP!$B$21:$U$21,MATCH(B14,Brand_LRP!$B$3:$U$3,0))*D14 -> 1.1371075
A15: 2027-11 | B15: 2027 | C15: 11 | D15: =IF(VALUE(B15)=Launch_3L,C15/78,1/12) -> 0.14102564 | E15: =INDEX(Brand_LRP!$B$18:$U$18,MATCH(B15,Brand_LRP!$B$3:$U$3,0))*D15 -> 15.607525 | F15: =INDEX(Brand_LRP!$B$19:$U$19,MATCH(B15,Brand_LRP!$B$3:$U$3,0))*12*D15 -> 93.645151 | G15: =F15*Compliance -> 88.962893 | H15: =INDEX(Brand_LRP!$B$21:$U$21,MATCH(B15,Brand_LRP!$B$3:$U$3,0))*D15 -> 1.2508183
A16: 2027-12 | B16: 2027 | C16: 12 | D16: =IF(VALUE(B16)=Launch_3L,C16/78,1/12) -> 0.15384615 | E16: =INDEX(Brand_LRP!$B$18:$U$18,MATCH(B16,Brand_LRP!$B$3:$U$3,0))*D16 -> 17.026391 | F16: =INDEX(Brand_LRP!$B$19:$U$19,MATCH(B16,Brand_LRP!$B$3:$U$3,0))*12*D16 -> 102.15835 | G16: =F16*Compliance -> 97.050429 | H16: =INDEX(Brand_LRP!$B$21:$U$21,MATCH(B16,Brand_LRP!$B$3:$U$3,0))*D16 -> 1.364529
... A28: 2028-12 | B28: 2028 | C28: 12 | D28: =IF(VALUE(B28)=Launch_3L,C28/78,1/12) -> 0.083333333 | E28: =INDEX(Brand_LRP!$B$18:$U$18,MATCH(B28,Brand_LRP!$B$3:$U$3,0))*D28 -> 38.390632 | F28: =INDEX(Brand_LRP!$B$19:$U$19,MATCH(B28,Brand_LRP!$B$3:$U$3,0))*12*D28 -> 230.34379 | G28: =F28*Compliance -> 218.8266 | H28: =INDEX(Brand_LRP!$B$21:$U$21,MATCH(B28,Brand_LRP!$B$3:$U$3,0))*D28 -> 3.076702
A30: Total 2027 | H30: =SUM(H5:H16) -> 8.8694387
A31: Total 2028 | H31: =SUM(H17:H28) -> 36.920424
